i3_layouts_fixed-0.13.3.data/scripts/i3l
i3l/__init__.py
i3l/cli.py
i3l/config.py
i3l/connect.py
i3l/corners.py
i3l/handlers.py
i3l/layouts.py
i3l/mover.py
i3l/options.py
i3l/splitter.py
i3l/state.py
i3l/ticks.py
test/__init__.py
test/test_config_parsing.py
test/test_layouts.py
i3_layouts_fixed-0.13.3.dist-info/LICENSE
i3_layouts_fixed-0.13.3.dist-info/METADATA
i3_layouts_fixed-0.13.3.dist-info/WHEEL
i3_layouts_fixed-0.13.3.dist-info/entry_points.txt
i3_layouts_fixed-0.13.3.dist-info/top_level.txt
i3_layouts_fixed-0.13.3.dist-info/RECORD
