Metadata-Version: 2.1
Name: i3-layouts-fixed
Version: 0.13.3
Summary: Dynamics layouts for i3wm
Home-page: http://github.com/eliep/i3-layouts-fixed
Author: eliep
Author-email: eprudhomme@gmail.com
License: MIT
Classifier: Programming Language :: Python :: 3
Classifier: License :: OSI Approved :: MIT License
Classifier: Operating System :: POSIX :: Linux
License-File: LICENSE
Requires-Dist: i3ipc
